Action.py
BaseTest.py
MSDBConnect.py
MicrosoftWebDriver.exe
Request.py
Setup.py
Suite.py
Test.py
chromedriver.exe
geckodriver.exe
SeleniumFramework.egg-info/PKG-INFO
SeleniumFramework.egg-info/SOURCES.txt
SeleniumFramework.egg-info/dependency_links.txt
SeleniumFramework.egg-info/requires.txt
SeleniumFramework.egg-info/top_level.txt