Metadata-Version: 1.2
Name: SeleniumFramework
Version: 0.1.8
Summary: Backend for run test suites from json definition files
Home-page: UNKNOWN
Author: Julio Reyes
Author-email: julio@truetech.com
License: UNKNOWN
Platform: UNKNOWN
Requires: selenium
Requires: pymssql
Requires: requests
Requires-Python: >3.6
